fu_scrapper/__init__.py
fu_scrapper/nba/__init__.py
fu_scrapper/nba/games.py
fu_scrapper/nba/players.py
fu_scrapper/nba/teams.py
fu_scrapper/tools/Scrapper.py
fu_scrapper/tools/__init__.py
fu_scrapper/tools/preformator.py
fu_scrapper/tools/tools.py
fu_scrapper-1.0.6.dist-info/LICENSE
fu_scrapper-1.0.6.dist-info/METADATA
fu_scrapper-1.0.6.dist-info/WHEEL
fu_scrapper-1.0.6.dist-info/top_level.txt
fu_scrapper-1.0.6.dist-info/RECORD
