Metadata-Version: 2.1
Name: fu-scrapper
Version: 1.0.6
Summary: NBA data Scrapper for stats analysis
Home-page: https://github.com/Endy02/fu-scrapper
Author: Fujyn
Author-email: fujyn.contact@gmail.com
License: UNKNOWN
Project-URL: Bug Tracker, https://github.com/Endy02/fu-scrapper/issues
Keywords: python,sports,data-analysis,csv
Platform: UNKNOWN
Classifier: Development Status :: 1 - Planning
Classifier: Intended Audience :: Developers
Classifier: Programming Language :: Python :: 3
Classifier: License :: OSI Approved :: MIT License
Classifier: Operating System :: Unix
Classifier: Operating System :: MacOS :: MacOS X
Classifier: Operating System :: Microsoft :: Windows
Requires-Python: >=3.7
License-File: LICENSE
Requires-Dist: pandas
Requires-Dist: numpy
Requires-Dist: requests
Requires-Dist: joblib
